raid/__init__.py
raid/_version.py
raid/detect.py
raid/evaluate.py
raid/utils.py
raid_bench-0.2.0.dist-info/METADATA
raid_bench-0.2.0.dist-info/WHEEL
raid_bench-0.2.0.dist-info/licenses/LICENSE
raid_bench-0.2.0.dist-info/RECORD
