Metadata-Version: 2.4
Name: raid-bench
Version: 0.2.0
Summary: RAID is the largest and most challenging benchmark for machine-generated text detectors.
Project-URL: Homepage, https://github.com/liamdugan/raid
Project-URL: Bug Tracker, https://github.com/liamdugan/raid/issues
Author-email: Liam Dugan <ldugan@seas.upenn.edu>, Andrew Zhu <andrew@zhu.codes>
License: MIT License
License-File: LICENSE
Classifier: Intended Audience :: Science/Research
Classifier: License :: OSI Approved :: MIT License
Classifier: Operating System :: OS Independent
Classifier: Programming Language :: Python :: 3
Classifier: Topic :: Scientific/Engineering :: Artificial Intelligence
Requires-Python: >=3.8
Requires-Dist: numpy~=1.26.4
Requires-Dist: pandas~=2.2.2
Requires-Dist: scikit-learn~=1.3.2
Requires-Dist: tqdm
